{
  "kpiSummary": {
    "totalRevenue": 2567890,
    "changeFromLastMonth": 12.5,
    "currency": "$",
    "targetValue": 3000000,
    "progressToOverallTarget": 85.6,
    "overallTarget": 3500000
  },
  "timeSeriesData": [
    {"date":"2024-01-01","value":3421,"channel":"directo","region":"na"},
    {"date":"2024-01-02","value":3339,"channel":"organico","region":"eu"},
    {"date":"2024-01-03","value":3400,"channel":"pagado","region":"asia"},
    {"date":"2024-01-04","value":3005,"channel":"referencia","region":"na"},
    {"date":"2024-01-05","value":2628,"channel":"directo","region":"eu"},
    {"date":"2024-01-06","value":2506,"channel":"organico","region":"asia"},
    {"date":"2024-01-07","value":2250,"channel":"pagado","region":"na"},
    {"date":"2024-01-08","value":2741,"channel":"referencia","region":"eu"},
    {"date":"2024-01-09","value":3264,"channel":"directo","region":"asia"},
    {"date":"2024-01-10","value":3490,"channel":"organico","region":"na"},
    {"date":"2024-01-11","value":3702,"channel":"pagado","region":"eu"},
    {"date":"2024-01-12","value":3730,"channel":"referencia","region":"asia"},
    {"date":"2024-01-13","value":4221,"channel":"directo","region":"na"},
    {"date":"2024-01-14","value":4530,"channel":"organico","region":"eu"},
    {"date":"2024-01-15","value":4180,"channel":"pagado","region":"asia"},
    {"date":"2024-01-16","value":4153,"channel":"referencia","region":"na"},
    {"date":"2024-01-17","value":4577,"channel":"directo","region":"eu"},
    {"date":"2024-01-18","value":4229,"channel":"organico","region":"asia"},
    {"date":"2024-01-19","value":4011,"channel":"pagado","region":"na"},
    {"date":"2024-01-20","value":3575,"channel":"referencia","region":"eu"},
    {"date":"2024-01-21","value":3478,"channel":"directo","region":"asia"},
    {"date":"2024-01-22","value":3876,"channel":"organico","region":"na"},
    {"date":"2024-01-23","value":3551,"channel":"pagado","region":"eu"},
    {"date":"2024-01-24","value":3722,"channel":"referencia","region":"asia"},
    {"date":"2024-01-25","value":4057,"channel":"directo","region":"na"},
    {"date":"2024-01-26","value":3616,"channel":"organico","region":"eu"},
    {"date":"2024-01-27","value":3874,"channel":"pagado","region":"asia"},
    {"date":"2024-01-28","value":4052,"channel":"referencia","region":"na"},
    {"date":"2024-01-29","value":4214,"channel":"directo","region":"eu"},
    {"date":"2024-01-30","value":4628,"channel":"organico","region":"asia"},
    {"date":"2024-01-31","value":4470,"channel":"pagado","region":"na"},
    {"date":"2024-02-01","value":4513,"channel":"referencia","region":"eu"},
    {"date":"2024-02-02","value":4164,"channel":"directo","region":"asia"},
    {"date":"2024-02-03","value":4457,"channel":"organico","region":"na"},
    {"date":"2024-02-04","value":4123,"channel":"pagado","region":"eu"},
    {"date":"2024-02-05","value":3974,"channel":"referencia","region":"asia"},
    {"date":"2024-02-06","value":4004,"channel":"directo","region":"na"},
    {"date":"2024-02-07","value":4146,"channel":"organico","region":"eu"},
    {"date":"2024-02-08","value":4145,"channel":"pagado","region":"asia"},
    {"date":"2024-02-09","value":4072,"channel":"referencia","region":"na"},
    {"date":"2024-02-10","value":3923,"channel":"directo","region":"eu"},
    {"date":"2024-02-11","value":4237,"channel":"organico","region":"asia"},
    {"date":"2024-02-12","value":4210,"channel":"pagado","region":"na"},
    {"date":"2024-02-13","value":3877,"channel":"referencia","region":"eu"},
    {"date":"2024-02-14","value":3496,"channel":"directo","region":"asia"},
    {"date":"2024-02-15","value":3808,"channel":"organico","region":"na"},
    {"date":"2024-02-16","value":3487,"channel":"pagado","region":"eu"},
    {"date":"2024-02-17","value":3453,"channel":"referencia","region":"asia"},
    {"date":"2024-02-18","value":3593,"channel":"directo","region":"na"},
    {"date":"2024-02-19","value":3224,"channel":"organico","region":"eu"},
    {"date":"2024-02-20","value":3348,"channel":"pagado","region":"asia"},
    {"date":"2024-02-21","value":3633,"channel":"referencia","region":"na"},
    {"date":"2024-02-22","value":3693,"channel":"directo","region":"eu"},
    {"date":"2024-02-23","value":3393,"channel":"organico","region":"asia"},
    {"date":"2024-02-24","value":3392,"channel":"pagado","region":"na"},
    {"date":"2024-02-25","value":3047,"channel":"referencia","region":"eu"},
    {"date":"2024-02-26","value":3401,"channel":"directo","region":"asia"},
    {"date":"2024-02-27","value":2962,"channel":"organico","region":"na"},
    {"date":"2024-02-28","value":3275,"channel":"pagado","region":"eu"},
    {"date":"2024-02-29","value":2928,"channel":"referencia","region":"asia"},
    {"date":"2024-03-01","value":3005,"channel":"directo","region":"na"},
    {"date":"2024-03-02","value":2623,"channel":"organico","region":"eu"},
    {"date":"2024-03-03","value":2583,"channel":"pagado","region":"asia"},
    {"date":"2024-03-04","value":2204,"channel":"referencia","region":"na"},
    {"date":"2024-03-05","value":1980,"channel":"directo","region":"eu"},
    {"date":"2024-03-06","value":2286,"channel":"organico","region":"asia"},
    {"date":"2024-03-07","value":1978,"channel":"pagado","region":"na"},
    {"date":"2024-03-08","value":1797,"channel":"referencia","region":"eu"},
    {"date":"2024-03-09","value":1861,"channel":"directo","region":"asia"},
    {"date":"2024-03-10","value":2097,"channel":"organico","region":"na"},
    {"date":"2024-03-11","value":2471,"channel":"pagado","region":"eu"},
    {"date":"2024-03-12","value":2135,"channel":"referencia","region":"asia"},
    {"date":"2024-03-13","value":2234,"channel":"directo","region":"na"},
    {"date":"2024-03-14","value":2397,"channel":"organico","region":"eu"},
    {"date":"2024-03-15","value":2595,"channel":"pagado","region":"asia"},
    {"date":"2024-03-16","value":2872,"channel":"referencia","region":"na"},
    {"date":"2024-03-17","value":2811,"channel":"directo","region":"eu"},
    {"date":"2024-03-18","value":2658,"channel":"organico","region":"asia"},
    {"date":"2024-03-19","value":2497,"channel":"pagado","region":"na"},
    {"date":"2024-03-20","value":2802,"channel":"referencia","region":"eu"},
    {"date":"2024-03-21","value":2884,"channel":"directo","region":"asia"},
    {"date":"2024-03-22","value":2899,"channel":"organico","region":"na"},
    {"date":"2024-03-23","value":2546,"channel":"pagado","region":"eu"},
    {"date":"2024-03-24","value":2931,"channel":"referencia","region":"asia"},
    {"date":"2024-03-25","value":3318,"channel":"directo","region":"na"},
    {"date":"2024-03-26","value":2975,"channel":"organico","region":"eu"},
    {"date":"2024-03-27","value":3047,"channel":"pagado","region":"asia"},
    {"date":"2024-03-28","value":3283,"channel":"referencia","region":"na"},
    {"date":"2024-03-29","value":2930,"channel":"directo","region":"eu"},
    {"date":"2024-03-30","value":2896,"channel":"organico","region":"asia"},
    {"date":"2024-03-31","value":3292,"channel":"pagado","region":"na"},
    {"date":"2024-04-01","value":3401,"channel":"referencia","region":"eu"},
    {"date":"2024-04-02","value":3063,"channel":"directo","region":"asia"},
    {"date":"2024-04-03","value":3040,"channel":"organico","region":"na"},
    {"date":"2024-04-04","value":3095,"channel":"pagado","region":"eu"},
    {"date":"2024-04-05","value":3297,"channel":"referencia","region":"asia"},
    {"date":"2024-04-06","value":3696,"channel":"directo","region":"na"},
    {"date":"2024-04-07","value":3704,"channel":"organico","region":"eu"},
    {"date":"2024-04-08","value":3434,"channel":"pagado","region":"asia"},
    {"date":"2024-04-09","value":3510,"channel":"referencia","region":"na"},
    {"date":"2024-04-10","value":3183,"channel":"directo","region":"eu"},
    {"date":"2024-04-11","value":3519,"channel":"organico","region":"asia"},
    {"date":"2024-04-12","value":3912,"channel":"pagado","region":"na"},
    {"date":"2024-04-13","value":3548,"channel":"referencia","region":"eu"},
    {"date":"2024-04-14","value":3926,"channel":"directo","region":"asia"},
    {"date":"2024-04-15","value":3736,"channel":"organico","region":"na"},
    {"date":"2024-04-16","value":3692,"channel":"pagado","region":"eu"},
    {"date":"2024-04-17","value":3789,"channel":"referencia","region":"asia"},
    {"date":"2024-04-18","value":3936,"channel":"directo","region":"na"},
    {"date":"2024-04-19","value":4233,"channel":"organico","region":"eu"},
    {"date":"2024-04-20","value":4360,"channel":"pagado","region":"asia"},
    {"date":"2024-04-21","value":4015,"channel":"referencia","region":"na"},
    {"date":"2024-04-22","value":4223,"channel":"directo","region":"eu"},
    {"date":"2024-04-23","value":4317,"channel":"organico","region":"asia"},
    {"date":"2024-04-24","value":4330,"channel":"pagado","region":"na"},
    {"date":"2024-04-25","value":4196,"channel":"referencia","region":"eu"},
    {"date":"2024-04-26","value":4579,"channel":"directo","region":"asia"},
    {"date":"2024-04-27","value":4254,"channel":"organico","region":"na"},
    {"date":"2024-04-28","value":4526,"channel":"pagado","region":"eu"},
    {"date":"2024-04-29","value":4160,"channel":"referencia","region":"asia"},
    {"date":"2024-04-30","value":4551,"channel":"directo","region":"na"},
    {"date":"2024-05-01","value":4202,"channel":"organico","region":"eu"},
    {"date":"2024-05-02","value":4510,"channel":"pagado","region":"asia"},
    {"date":"2024-05-03","value":4184,"channel":"referencia","region":"na"},
    {"date":"2024-05-04","value":4339,"channel":"directo","region":"eu"},
    {"date":"2024-05-05","value":4062,"channel":"organico","region":"asia"},
    {"date":"2024-05-06","value":3958,"channel":"pagado","region":"na"},
    {"date":"2024-05-07","value":4335,"channel":"referencia","region":"eu"},
    {"date":"2024-05-08","value":4043,"channel":"directo","region":"asia"},
    {"date":"2024-05-09","value":3820,"channel":"organico","region":"na"},
    {"date":"2024-05-10","value":3684,"channel":"pagado","region":"eu"},
    {"date":"2024-05-11","value":3470,"channel":"referencia","region":"asia"},
    {"date":"2024-05-12","value":3232,"channel":"directo","region":"na"},
    {"date":"2024-05-13","value":3423,"channel":"organico","region":"eu"},
    {"date":"2024-05-14","value":3707,"channel":"pagado","region":"asia"},
    {"date":"2024-05-15","value":3723,"channel":"referencia","region":"na"},
    {"date":"2024-05-16","value":3692,"channel":"directo","region":"eu"},
    {"date":"2024-05-17","value":3356,"channel":"organico","region":"asia"},
    {"date":"2024-05-18","value":3062,"channel":"pagado","region":"na"},
    {"date":"2024-05-19","value":3432,"channel":"referencia","region":"eu"},
    {"date":"2024-05-20","value":3175,"channel":"directo","region":"asia"},
    {"date":"2024-05-21","value":3262,"channel":"organico","region":"na"},
    {"date":"2024-05-22","value":3011,"channel":"pagado","region":"eu"},
    {"date":"2024-05-23","value":2671,"channel":"referencia","region":"asia"},
    {"date":"2024-05-24","value":2790,"channel":"directo","region":"na"},
    {"date":"2024-05-25","value":3158,"channel":"organico","region":"eu"},
    {"date":"2024-05-26","value":3159,"channel":"pagado","region":"asia"},
    {"date":"2024-05-27","value":3175,"channel":"referencia","region":"na"},
    {"date":"2024-05-28","value":3358,"channel":"directo","region":"eu"},
    {"date":"2024-05-29","value":3627,"channel":"organico","region":"asia"},
    {"date":"2024-05-30","value":3242,"channel":"pagado","region":"na"},
    {"date":"2024-05-31","value":3058,"channel":"referencia","region":"eu"},
    {"date":"2024-06-01","value":0,"channel":"directo","region":"asia"}, 
    {"date":"2024-06-02","value":0,"channel":"organico","region":"na"},
    {"date":"2024-06-03","value":0,"channel":"pagado","region":"eu"},
    {"date":"2024-06-04","value":0,"channel":"referencia","region":"asia"},
    {"date":"2024-06-05","value":0,"channel":"directo","region":"na"},
    {"date":"2024-06-06","value":0,"channel":"organico","region":"eu"},
    {"date":"2024-06-07","value":0,"channel":"pagado","region":"asia"},
    {"date":"2024-06-08","value":0,"channel":"referencia","region":"na"},
    {"date":"2024-06-09","value":0,"channel":"directo","region":"eu"},
    {"date":"2024-06-10","value":0,"channel":"organico","region":"asia"},
    {"date":"2024-06-11","value":0,"channel":"pagado","region":"na"},
    {"date":"2024-06-12","value":0,"channel":"referencia","region":"eu"},
    {"date":"2024-06-13","value":0,"channel":"directo","region":"asia"},
    {"date":"2024-06-14","value":0,"channel":"organico","region":"na"},
    {"date":"2024-06-15","value":0,"channel":"pagado","region":"eu"},
    {"date":"2024-06-16","value":0,"channel":"referencia","region":"asia"},
    {"date":"2024-06-17","value":0,"channel":"directo","region":"na"},
    {"date":"2024-06-18","value":0,"channel":"organico","region":"eu"},
    {"date":"2024-06-19","value":0,"channel":"pagado","region":"asia"},
    {"date":"2024-06-20","value":0,"channel":"referencia","region":"na"},
    {"date":"2024-06-21","value":0,"channel":"directo","region":"eu"},
    {"date":"2024-06-22","value":0,"channel":"organico","region":"asia"},
    {"date":"2024-06-23","value":0,"channel":"pagado","region":"na"},
    {"date":"2024-06-24","value":0,"channel":"referencia","region":"eu"},
    {"date":"2024-06-25","value":0,"channel":"directo","region":"asia"},
    {"date":"2024-06-26","value":0,"channel":"organico","region":"na"},
    {"date":"2024-06-27","value":0,"channel":"pagado","region":"eu"},
    {"date":"2024-06-28","value":0,"channel":"referencia","region":"asia"},
    {"date":"2024-06-29","value":0,"channel":"directo","region":"na"},
    {"date":"2024-06-30","value":0,"channel":"organico","region":"eu"},
    {"date":"2024-07-01","value":0,"channel":"pagado","region":"asia"},
    {"date":"2024-07-02","value":0,"channel":"referencia","region":"na"},
    {"date":"2024-07-03","value":0,"channel":"directo","region":"eu"},
    {"date":"2024-07-04","value":0,"channel":"organico","region":"asia"},
    {"date":"2024-07-05","value":0,"channel":"pagado","region":"na"},
    {"date":"2024-07-06","value":0,"channel":"referencia","region":"eu"},
    {"date":"2024-07-07","value":0,"channel":"directo","region":"asia"},
    {"date":"2024-07-08","value":0,"channel":"organico","region":"na"},
    {"date":"2024-07-09","value":0,"channel":"pagado","region":"eu"},
    {"date":"2024-07-10","value":0,"channel":"referencia","region":"asia"},
    {"date":"2024-07-11","value":0,"channel":"directo","region":"na"},
    {"date":"2024-07-12","value":0,"channel":"organico","region":"eu"},
    {"date":"2024-07-13","value":0,"channel":"pagado","region":"asia"},
    {"date":"2024-07-14","value":0,"channel":"referencia","region":"na"},
    {"date":"2024-07-15","value":0,"channel":"directo","region":"eu"},
    {"date":"2024-07-16","value":0,"channel":"organico","region":"asia"},
    {"date":"2024-07-17","value":0,"channel":"pagado","region":"na"},
    {"date":"2024-07-18","value":0,"channel":"referencia","region":"eu"},
    {"date":"2024-07-19","value":0,"channel":"directo","region":"asia"},
    {"date":"2024-07-20","value":0,"channel":"organico","region":"na"},
    {"date":"2024-07-21","value":0,"channel":"pagado","region":"eu"},
    {"date":"2024-07-22","value":0,"channel":"referencia","region":"asia"},
    {"date":"2024-07-23","value":0,"channel":"directo","region":"na"},
    {"date":"2024-07-24","value":0,"channel":"organico","region":"eu"},
    {"date":"2024-07-25","value":0,"channel":"pagado","region":"asia"},
    {"date":"2024-07-26","value":0,"channel":"referencia","region":"na"},
    {"date":"2024-07-27","value":0,"channel":"directo","region":"eu"},
    {"date":"2024-07-28","value":0,"channel":"organico","region":"asia"},
    {"date":"2024-07-29","value":0,"channel":"pagado","region":"na"},
    {"date":"2024-07-30","value":0,"channel":"referencia","region":"eu"},
    {"date":"2024-07-31","value":0,"channel":"directo","region":"asia"},
    {"date":"2024-08-01","value":0,"channel":"organico","region":"na"},
    {"date":"2024-08-02","value":0,"channel":"pagado","region":"eu"},
    {"date":"2024-08-03","value":0,"channel":"referencia","region":"asia"},
    {"date":"2024-08-04","value":0,"channel":"directo","region":"na"},
    {"date":"2024-08-05","value":0,"channel":"organico","region":"eu"},
    {"date":"2024-08-06","value":0,"channel":"pagado","region":"asia"},
    {"date":"2024-08-07","value":0,"channel":"referencia","region":"na"},
    {"date":"2024-08-08","value":0,"channel":"directo","region":"eu"},
    {"date":"2024-08-09","value":0,"channel":"organico","region":"asia"},
    {"date":"2024-08-10","value":0,"channel":"pagado","region":"na"},
    {"date":"2024-08-11","value":0,"channel":"referencia","region":"eu"},
    {"date":"2024-08-12","value":0,"channel":"directo","region":"asia"},
    {"date":"2024-08-13","value":0,"channel":"organico","region":"na"},
    {"date":"2024-08-14","value":0,"channel":"pagado","region":"eu"},
    {"date":"2024-08-15","value":0,"channel":"referencia","region":"asia"},
    {"date":"2024-08-16","value":0,"channel":"directo","region":"na"},
    {"date":"2024-08-17","value":0,"channel":"organico","region":"eu"},
    {"date":"2024-08-18","value":0,"channel":"pagado","region":"asia"},
    {"date":"2024-08-19","value":0,"channel":"referencia","region":"na"},
    {"date":"2024-08-20","value":0,"channel":"directo","region":"eu"},
    {"date":"2024-08-21","value":0,"channel":"organico","region":"asia"},
    {"date":"2024-08-22","value":0,"channel":"pagado","region":"na"},
    {"date":"2024-08-23","value":0,"channel":"referencia","region":"eu"},
    {"date":"2024-08-24","value":0,"channel":"directo","region":"asia"},
    {"date":"2024-08-25","value":0,"channel":"organico","region":"na"},
    {"date":"2024-08-26","value":0,"channel":"pagado","region":"eu"},
    {"date":"2024-08-27","value":0,"channel":"referencia","region":"asia"},
    {"date":"2024-08-28","value":0,"channel":"directo","region":"na"},
    {"date":"2024-08-29","value":0,"channel":"organico","region":"eu"},
    {"date":"2024-08-30","value":0,"channel":"pagado","region":"asia"},
    {"date":"2024-08-31","value":0,"channel":"referencia","region":"na"},
    {"date":"2024-09-01","value":0,"channel":"directo","region":"eu"},
    {"date":"2024-09-02","value":0,"channel":"organico","region":"asia"},
    {"date":"2024-09-03","value":0,"channel":"pagado","region":"na"},
    {"date":"2024-09-04","value":0,"channel":"referencia","region":"eu"},
    {"date":"2024-09-05","value":0,"channel":"directo","region":"asia"},
    {"date":"2024-09-06","value":0,"channel":"organico","region":"na"},
    {"date":"2024-09-07","value":0,"channel":"pagado","region":"eu"},
    {"date":"2024-09-08","value":0,"channel":"referencia","region":"asia"},
    {"date":"2024-09-09","value":0,"channel":"directo","region":"na"},
    {"date":"2024-09-10","value":0,"channel":"organico","region":"eu"},
    {"date":"2024-09-11","value":0,"channel":"pagado","region":"asia"},
    {"date":"2024-09-12","value":0,"channel":"referencia","region":"na"},
    {"date":"2024-09-13","value":0,"channel":"directo","region":"eu"},
    {"date":"2024-09-14","value":0,"channel":"organico","region":"asia"},
    {"date":"2024-09-15","value":0,"channel":"pagado","region":"na"},
    {"date":"2024-09-16","value":0,"channel":"referencia","region":"eu"},
    {"date":"2024-09-17","value":0,"channel":"directo","region":"asia"},
    {"date":"2024-09-18","value":0,"channel":"organico","region":"na"},
    {"date":"2024-09-19","value":0,"channel":"pagado","region":"eu"},
    {"date":"2024-09-20","value":0,"channel":"referencia","region":"asia"},
    {"date":"2024-09-21","value":0,"channel":"directo","region":"na"},
    {"date":"2024-09-22","value":0,"channel":"organico","region":"eu"},
    {"date":"2024-09-23","value":0,"channel":"pagado","region":"asia"},
    {"date":"2024-09-24","value":0,"channel":"referencia","region":"na"},
    {"date":"2024-09-25","value":0,"channel":"directo","region":"eu"},
    {"date":"2024-09-26","value":0,"channel":"organico","region":"asia"},
    {"date":"2024-09-27","value":0,"channel":"pagado","region":"na"},
    {"date":"2024-09-28","value":0,"channel":"referencia","region":"eu"},
    {"date":"2024-09-29","value":0,"channel":"directo","region":"asia"},
    {"date":"2024-09-30","value":0,"channel":"organico","region":"na"},
    {"date":"2024-10-01","value":0,"channel":"pagado","region":"eu"},
    {"date":"2024-10-02","value":0,"channel":"referencia","region":"asia"},
    {"date":"2024-10-03","value":0,"channel":"directo","region":"na"},
    {"date":"2024-10-04","value":0,"channel":"organico","region":"eu"},
    {"date":"2024-10-05","value":0,"channel":"pagado","region":"asia"},
    {"date":"2024-10-06","value":0,"channel":"referencia","region":"na"},
    {"date":"2024-10-07","value":0,"channel":"directo","region":"eu"},
    {"date":"2024-10-08","value":0,"channel":"organico","region":"asia"},
    {"date":"2024-10-09","value":0,"channel":"pagado","region":"na"},
    {"date":"2024-10-10","value":0,"channel":"referencia","region":"eu"},
    {"date":"2024-10-11","value":0,"channel":"directo","region":"asia"},
    {"date":"2024-10-12","value":0,"channel":"organico","region":"na"},
    {"date":"2024-10-13","value":0,"channel":"pagado","region":"eu"},
    {"date":"2024-10-14","value":0,"channel":"referencia","region":"asia"},
    {"date":"2024-10-15","value":0,"channel":"directo","region":"na"},
    {"date":"2024-10-16","value":0,"channel":"organico","region":"eu"},
    {"date":"2024-10-17","value":0,"channel":"pagado","region":"asia"},
    {"date":"2024-10-18","value":0,"channel":"referencia","region":"na"},
    {"date":"2024-10-19","value":0,"channel":"directo","region":"eu"},
    {"date":"2024-10-20","value":0,"channel":"organico","region":"asia"},
    {"date":"2024-10-21","value":0,"channel":"pagado","region":"na"},
    {"date":"2024-10-22","value":0,"channel":"referencia","region":"eu"},
    {"date":"2024-10-23","value":0,"channel":"directo","region":"asia"},
    {"date":"2024-10-24","value":0,"channel":"organico","region":"na"},
    {"date":"2024-10-25","value":0,"channel":"pagado","region":"eu"},
    {"date":"2024-10-26","value":0,"channel":"referencia","region":"asia"},
    {"date":"2024-10-27","value":0,"channel":"directo","region":"na"},
    {"date":"2024-10-28","value":0,"channel":"organico","region":"eu"},
    {"date":"2024-10-29","value":0,"channel":"pagado","region":"asia"},
    {"date":"2024-10-30","value":0,"channel":"referencia","region":"na"},
    {"date":"2024-10-31","value":0,"channel":"directo","region":"eu"},
    {"date":"2024-11-01","value":0,"channel":"organico","region":"asia"},
    {"date":"2024-11-02","value":0,"channel":"pagado","region":"na"},
    {"date":"2024-11-03","value":0,"channel":"referencia","region":"eu"},
    {"date":"2024-11-04","value":0,"channel":"directo","region":"asia"},
    {"date":"2024-11-05","value":0,"channel":"organico","region":"na"},
    {"date":"2024-11-06","value":0,"channel":"pagado","region":"eu"},
    {"date":"2024-11-07","value":0,"channel":"referencia","region":"asia"},
    {"date":"2024-11-08","value":0,"channel":"directo","region":"na"},
    {"date":"2024-11-09","value":0,"channel":"organico","region":"eu"},
    {"date":"2024-11-10","value":0,"channel":"pagado","region":"asia"},
    {"date":"2024-11-11","value":0,"channel":"referencia","region":"na"},
    {"date":"2024-11-12","value":0,"channel":"directo","region":"eu"},
    {"date":"2024-11-13","value":0,"channel":"organico","region":"asia"},
    {"date":"2024-11-14","value":0,"channel":"pagado","region":"na"},
    {"date":"2024-11-15","value":0,"channel":"referencia","region":"eu"},
    {"date":"2024-11-16","value":0,"channel":"directo","region":"asia"},
    {"date":"2024-11-17","value":0,"channel":"organico","region":"na"},
    {"date":"2024-11-18","value":0,"channel":"pagado","region":"eu"},
    {"date":"2024-11-19","value":0,"channel":"referencia","region":"asia"},
    {"date":"2024-11-20","value":0,"channel":"directo","region":"na"},
    {"date":"2024-11-21","value":0,"channel":"organico","region":"eu"},
    {"date":"2024-11-22","value":0,"channel":"pagado","region":"asia"},
    {"date":"2024-11-23","value":0,"channel":"referencia","region":"na"},
    {"date":"2024-11-24","value":0,"channel":"directo","region":"eu"},
    {"date":"2024-11-25","value":0,"channel":"organico","region":"asia"},
    {"date":"2024-11-26","value":0,"channel":"pagado","region":"na"},
    {"date":"2024-11-27","value":0,"channel":"referencia","region":"eu"},
    {"date":"2024-11-28","value":0,"channel":"directo","region":"asia"},
    {"date":"2024-11-29","value":0,"channel":"organico","region":"na"},
    {"date":"2024-11-30","value":0,"channel":"pagado","region":"eu"},
    {"date":"2024-12-01","value":0,"channel":"referencia","region":"asia"},
    {"date":"2024-12-02","value":0,"channel":"directo","region":"na"},
    {"date":"2024-12-03","value":0,"channel":"organico","region":"eu"},
    {"date":"2024-12-04","value":0,"channel":"pagado","region":"asia"},
    {"date":"2024-12-05","value":0,"channel":"referencia","region":"na"},
    {"date":"2024-12-06","value":0,"channel":"directo","region":"eu"},
    {"date":"2024-12-07","value":0,"channel":"organico","region":"asia"},
    {"date":"2024-12-08","value":0,"channel":"pagado","region":"na"},
    {"date":"2024-12-09","value":0,"channel":"referencia","region":"eu"},
    {"date":"2024-12-10","value":0,"channel":"directo","region":"asia"},
    {"date":"2024-12-11","value":0,"channel":"organico","region":"na"},
    {"date":"2024-12-12","value":0,"channel":"pagado","region":"eu"},
    {"date":"2024-12-13","value":0,"channel":"referencia","region":"asia"},
    {"date":"2024-12-14","value":0,"channel":"directo","region":"na"},
    {"date":"2024-12-15","value":0,"channel":"organico","region":"eu"},
    {"date":"2024-12-16","value":0,"channel":"pagado","region":"asia"},
    {"date":"2024-12-17","value":0,"channel":"referencia","region":"na"},
    {"date":"2024-12-18","value":0,"channel":"directo","region":"eu"},
    {"date":"2024-12-19","value":0,"channel":"organico","region":"asia"},
    {"date":"2024-12-20","value":0,"channel":"pagado","region":"na"},
    {"date":"2024-12-21","value":0,"channel":"referencia","region":"eu"},
    {"date":"2024-12-22","value":0,"channel":"directo","region":"asia"},
    {"date":"2024-12-23","value":0,"channel":"organico","region":"na"},
    {"date":"2024-12-24","value":0,"channel":"pagado","region":"eu"},
    {"date":"2024-12-25","value":0,"channel":"referencia","region":"asia"},
    {"date":"2024-12-26","value":0,"channel":"directo","region":"na"},
    {"date":"2024-12-27","value":0,"channel":"organico","region":"eu"},
    {"date":"2024-12-28","value":0,"channel":"pagado","region":"asia"},
    {"date":"2024-12-29","value":0,"channel":"referencia","region":"na"},
    {"date":"2024-12-30","value":0,"channel":"directo","region":"eu"},
    {"date":"2024-12-31","value":0,"channel":"organico","region":"asia"},
    {"date":"2025-01-01","value":2404,"channel":"pagado","region":"na"},
    {"date":"2025-01-02","value":2230,"channel":"referencia","region":"eu"},
    {"date":"2025-01-03","value":1882,"channel":"directo","region":"asia"},
    {"date":"2025-01-04","value":2061,"channel":"organico","region":"na"},
    {"date":"2025-01-05","value":2378,"channel":"pagado","region":"eu"},
    {"date":"2025-01-06","value":2033,"channel":"referencia","region":"asia"},
    {"date":"2025-01-07","value":1836,"channel":"directo","region":"na"},
    {"date":"2025-01-08","value":2157,"channel":"organico","region":"eu"},
    {"date":"2025-01-09","value":1821,"channel":"pagado","region":"asia"},
    {"date":"2025-01-10","value":2121,"channel":"referencia","region":"na"},
    {"date":"2025-01-11","value":1909,"channel":"directo","region":"eu"},
    {"date":"2025-01-12","value":2244,"channel":"organico","region":"asia"},
    {"date":"2025-01-13","value":2582,"channel":"pagado","region":"na"},
    {"date":"2025-01-14","value":2523,"channel":"referencia","region":"eu"},
    {"date":"2025-01-15","value":2165,"channel":"directo","region":"asia"},
    {"date":"2025-01-16","value":1867,"channel":"organico","region":"na"},
    {"date":"2025-01-17","value":2005,"channel":"pagado","region":"eu"},
    {"date":"2025-01-18","value":2047,"channel":"referencia","region":"asia"},
    {"date":"2025-01-19","value":1982,"channel":"directo","region":"na"},
    {"date":"2025-01-20","value":2320,"channel":"organico","region":"eu"},
    {"date":"2025-01-21","value":2626,"channel":"pagado","region":"asia"},
    {"date":"2025-01-22","value":2914,"channel":"referencia","region":"na"},
    {"date":"2025-01-23","value":2833,"channel":"directo","region":"eu"},
    {"date":"2025-01-24","value":2469,"channel":"organico","region":"asia"},
    {"date":"2025-01-25","value":2810,"channel":"pagado","region":"na"},
    {"date":"2025-01-26","value":2496,"channel":"referencia","region":"eu"},
    {"date":"2025-01-27","value":2227,"channel":"directo","region":"asia"},
    {"date":"2025-01-28","value":2438,"channel":"organico","region":"na"},
    {"date":"2025-01-29","value":2392,"channel":"pagado","region":"eu"},
    {"date":"2025-01-30","value":2054,"channel":"referencia","region":"asia"}
  ],
  "channelData": [
    { "name": "Directo", "value": 35.5, "channel": "directo" },
    { "name": "Búsqueda Orgánica", "value": 28.2, "channel": "organico" },
    { "name": "Búsqueda Pagada", "value": 18.7, "channel": "pagado" },
    { "name": "Referencia", "value": 17.6, "channel": "referencia" }
  ],
  "stackedComboData": {
    "categories": ["Q1 2024", "Q2 2024", "Q3 2024", "Q4 2024", "Q1 2025"],
    "series": [
      { "name": "Ventas", "type": "column", "data": [501000, 572000, 616000, 636000, 705000] },
      { "name": "Costos", "type": "column", "data": [200000, 230000, 247000, 254000, 282000] },
      { "name": "Beneficio", "type": "line", "data": [301000, 342000, 369000, 382000, 423000] }
    ]
  },
  "boxplotData": [
    { "x": "NA", "y": [120000, 145000, 165000, 185000, 210000] },
    { "x": "EU", "y": [110000, 135000, 155000, 175000, 195000] },
    { "x": "ASIA", "y": [125000, 150000, 170000, 190000, 215000] }
  ],
  "trendlineTargetRangeData": [],
  "progressLineTrendValue": 190000,
  "stackedBar100Data": {
    "categories": ["Q1", "Q2", "Q3", "Q4"],
    "series": [
      { "name": "Producto A", "data": [44, 42, 47, 45] },
      { "name": "Producto B", "data": [33, 35, 30, 32] },
      { "name": "Producto C", "data": [23, 23, 23, 23] }
    ]
  },
  "stackedArea100Data": {
    "seriesFactors": [
      { "name": "Canal A", "factor": 0.4, "base": 20 },
      { "name": "Canal B", "factor": 0.3, "base": 15 },
      { "name": "Canal C", "factor": 0.3, "base": 10 }
    ],
    "numPoints": 15,
    "startDate": "2024-01-01"
  },
  "productCategoryRevenue": {
    "categories": ["Electrónicos", "Ropa", "Hogar", "Deportes"],
    "series": [
      { "name": "Actual", "data": [890000, 567000, 445000, 323000] },
      { "name": "Anterior", "data": [745000, 523000, 398000, 289000] }
    ],
    "totalCurrentPeriod": 2225000,
    "totalPreviousPeriod": 1955000
  }
}